{
	"ImportPath": "github.com/margaritagomez/recipes-back",
	"GoVersion": "go1.11",
	"GodepVersion": "v80",
	"Packages": [
		"./..."
	],
	"Deps": [
		{
			"ImportPath": "github.com/gorilla/mux",
			"Comment": "v1.6.2-9-g9e1f595",
			"Rev": "9e1f5955c0d22b55d9e20d6faa28589f83b2faca"
		},
		{
			"ImportPath": "gopkg.in/mgo.v2",
			"Comment": "r2016.08.01-7-g9856a29",
			"Rev": "9856a29383ce1c59f308dd1cf0363a79b5bef6b5"
		},
		{
			"ImportPath": "gopkg.in/mgo.v2/bson",
			"Comment": "r2016.08.01-7-g9856a29",
			"Rev": "9856a29383ce1c59f308dd1cf0363a79b5bef6b5"
		},
		{
			"ImportPath": "gopkg.in/mgo.v2/dbtest",
			"Comment": "r2016.08.01-7-g9856a29",
			"Rev": "9856a29383ce1c59f308dd1cf0363a79b5bef6b5"
		},
		{
			"ImportPath": "gopkg.in/mgo.v2/internal/json",
			"Comment": "r2016.08.01-7-g9856a29",
			"Rev": "9856a29383ce1c59f308dd1cf0363a79b5bef6b5"
		},
		{
			"ImportPath": "gopkg.in/mgo.v2/internal/sasl",
			"Comment": "r2016.08.01-7-g9856a29",
			"Rev": "9856a29383ce1c59f308dd1cf0363a79b5bef6b5"
		},
		{
			"ImportPath": "gopkg.in/mgo.v2/internal/scram",
			"Comment": "r2016.08.01-7-g9856a29",
			"Rev": "9856a29383ce1c59f308dd1cf0363a79b5bef6b5"
		},
		{
			"ImportPath": "gopkg.in/tomb.v2",
			"Rev": "d5d1b5820637886def9eef33e03a27a9f166942c"
		}
	]
}
